README.md
setup.py
pvlv/__init__.py
pvlv/pvlv.py
pvlv.egg-info/PKG-INFO
pvlv.egg-info/SOURCES.txt
pvlv.egg-info/dependency_links.txt
pvlv.egg-info/requires.txt
pvlv.egg-info/top_level.txt
pvlv/debug/__init__.py
pvlv/debug/execution_time.py
pvlv/handlers/__init__.py
pvlv/handlers/base_handler.py
pvlv/handlers/img_handler.py
pvlv/handlers/text_handler.py
pvlv/handlers/vocal_handler.py
pvlv/handlers/antispam/__init__.py
pvlv/handlers/antispam/antispam_reply.py
pvlv/handlers/level_up/__init__.py
pvlv/handlers/level_up/level_up_reply.py
pvlv/handlers/speech_to_text/__init__.py
pvlv/handlers/speech_to_text/speech_to_text.py
pvlv/static/__init__.py
pvlv/static/configurations.py
pvlv/static/settings.py
pvlv/static/types.py