Metadata-Version: 2.1
Name: pvlv
Version: 0.0.1
Summary: Bot Framework for Pavlov
Home-page: https://github.com/The-Pavlov-Project/pvlv
Author: AbbestiaDC
Author-email: not.simone.scuola@outlook.com
License: LGPLv3
Platform: UNKNOWN
Classifier: Programming Language :: Python
Classifier: License :: OSI Approved :: GNU General Public License v3 (GPLv3)
Requires-Python: >=3.6
